abstract_math/__init__.py
abstract_math/derive_tokens.py
abstract_math/safe_math.py
abstract_math/flask_scripts/__init__.py
abstract_math/flask_scripts/flask_utils.py
abstract_math/flask_scripts/make_flask.py
abstract_math/solar_math/__init__.py
abstract_math/solar_math/flask_utils.py
abstract_math/solar_math/main.py
abstract_math/solar_math/src/__init__.py
abstract_math/solar_math/src/imports.py
abstract_math/solar_math/src/constants/__init__.py
abstract_math/solar_math/src/constants/distance_constants.py
abstract_math/solar_math/src/constants/planet_constants.py
abstract_math/solar_math/src/constants/time_constants.py
abstract_math/solar_math/src/utils/__init__.py
abstract_math/solar_math/src/utils/escape_velocity.py
abstract_math/solar_math/src/utils/geometry_utils.py
abstract_math/solar_math/src/utils/velocity_utils.py
abstract_math-0.0.0.18.dist-info/METADATA
abstract_math-0.0.0.18.dist-info/WHEEL
abstract_math-0.0.0.18.dist-info/top_level.txt
abstract_math-0.0.0.18.dist-info/RECORD
